cbc_syslog/__init__.py
cbc_syslog/cli.py
cbc_syslog/core.py
cbc_syslog/util/__init__.py
cbc_syslog/util/carbon_black_cloud.py
cbc_syslog/util/config.py
cbc_syslog/util/example.py
cbc_syslog/util/output.py
cbc_syslog/util/transform.py
cbc_syslog-2.0.6.dist-info/LICENSE
cbc_syslog-2.0.6.dist-info/METADATA
cbc_syslog-2.0.6.dist-info/WHEEL
cbc_syslog-2.0.6.dist-info/entry_points.txt
cbc_syslog-2.0.6.dist-info/top_level.txt
cbc_syslog-2.0.6.dist-info/RECORD
