Metadata-Version: 2.1
Name: cbc-syslog
Version: 2.0.6
Summary: Syslog Connector for Carbon Black Cloud
Home-page: https://github.com/carbonblack/cbc-syslog
Author: Carbon Black Developer Network
Author-email: cb-developer-network@vmware.com
License: MIT
Keywords: carbonblack
Classifier: Intended Audience :: Developers
Classifier: License :: OSI Approved :: MIT License
Classifier: Programming Language :: Python :: 3
License-File: LICENSE
Requires-Dist: carbon-black-cloud-sdk >=1.5.5
Requires-Dist: Jinja2
Requires-Dist: psutil
Requires-Dist: tomli >=1.1.0 ; python_version < "3.11"
Provides-Extra: test
Requires-Dist: flask ; extra == 'test'
Requires-Dist: cryptography ; extra == 'test'
Requires-Dist: pytest ==7.2.1 ; extra == 'test'
Requires-Dist: coverage ==6.5.0 ; extra == 'test'
Requires-Dist: flake8 ==5.0.4 ; extra == 'test'
Requires-Dist: flake8-colors ==0.1.9 ; extra == 'test'
Requires-Dist: flake8-docstrings ==1.7.0 ; extra == 'test'
Requires-Dist: pre-commit >=2.15.0 ; extra == 'test'
Requires-Dist: freezegun ==1.2.2 ; extra == 'test'
Requires-Dist: proxy.py ==2.4.4 ; extra == 'test'
